clickhouse_cityhash/__init__.py
clickhouse_cityhash/cityhash.cpython-314-x86_64-linux-gnu.so
clickhouse_cityhash-1.0.2.5.dist-info/METADATA
clickhouse_cityhash-1.0.2.5.dist-info/WHEEL
clickhouse_cityhash-1.0.2.5.dist-info/top_level.txt
clickhouse_cityhash-1.0.2.5.dist-info/RECORD
clickhouse_cityhash-1.0.2.5.dist-info/licenses/LICENSE
