Metadata-Version: 2.4
Name: clickhouse-cityhash
Version: 1.0.2.5
Summary: Python-bindings for CityHash, a fast non-cryptographic hash algorithm
Home-page: https://github.com/xzkostyan/clickhouse-cityhash
Download-URL: https://github.com/xzkostyan/clickhouse-cityhash/tarball/master/1.0.2.5
Author: Alexander [Amper] Marshalov
Author-email: alone.amper+cityhash@gmail.com
License: MIT
Keywords: hash,hashing,cityhash
Classifier: Development Status :: 4 - Beta
Classifier: Operating System :: OS Independent
Classifier: Intended Audience :: Developers
Classifier: Intended Audience :: Science/Research
Classifier: License :: OSI Approved :: MIT License
Classifier: Programming Language :: C++
Classifier: Programming Language :: Cython
Classifier: Programming Language :: Python :: 2.7
Classifier: Programming Language :: Python :: 3.6
Classifier: Topic :: Internet
Classifier: Topic :: Scientific/Engineering
Classifier: Topic :: Scientific/Engineering :: Information Analysis
Classifier: Topic :: Software Development
Classifier: Topic :: Software Development :: Libraries :: Python Modules
Classifier: Topic :: Utilities
License-File: LICENSE
Dynamic: author
Dynamic: author-email
Dynamic: classifier
Dynamic: description
Dynamic: download-url
Dynamic: home-page
Dynamic: keywords
Dynamic: license
Dynamic: license-file
Dynamic: summary
